{
  "timestamp": "2025-06-05T15:11:00.000Z",
  "lastCommand": "git commit capacity field implementation",
  "currentFile": "property forms and views",
  "gitStatus": "clean - committed",
  "installedPackages": [
    "prisma",
    "@prisma/client", 
    "next",
    "react",
    "typescript",
    "tailwindcss",
    "@trpc/server",
    "@trpc/client",
    "zod",
    "react-hook-form"
  ],
  "migrationStatus": "applied - capacity field added",
  "currentPhase": "Property management enhancements",
  "completedTasks": [
    "Database schema update with capacity field",
    "Property API router validation update", 
    "New property form capacity input",
    "Edit property form capacity support",
    "Property list table capacity column",
    "Property details capacity display",
    "Manual testing verification",
    "Documentation updates",
    "Git commit and checkpoint creation"
  ],
  "pendingTasks": [
    "Await user feedback and next requirements",
    "Consider additional property features",
    "Test capacity field with real data"
  ],
  "lastFeature": "Property capacity field implementation",
  "serverStatus": "running on port 3333",
  "databaseStatus": "connected and migrated",
  "buildStatus": "successful"
}